KucoinPy/__init__.py
KucoinPy/classes.py
KucoinPy/http.py
KucoinPy/wrapper.py
KucoinPy/ws.py
KucoinPy-0.0.3.dist-info/LICENSE
KucoinPy-0.0.3.dist-info/METADATA
KucoinPy-0.0.3.dist-info/WHEEL
KucoinPy-0.0.3.dist-info/top_level.txt
KucoinPy-0.0.3.dist-info/RECORD
