Metadata-Version: 2.1
Name: KucoinPy
Version: 0.0.3
Summary: Probably the fastest kucoin API wrapper in python
Home-page: https://www.github.com/PrivatePandaCO/KucoinPy
Author: Parth Mittal
Author-email: parth@privatepanda.co
License: GNU GENERAL PUBLIC LICENSE Version 2
Project-URL: Documentation, https://github.com/PrivatePandaCO/KucoinPy/blob/master/README.md
Project-URL: Github, https://github.com/PrivatePandaCO/KucoinPy
Project-URL: Changelog, https://github.com/PrivatePandaCO/KucoinPy/blob/master/changelog.md
License-File: LICENSE
Requires-Dist: orjson
Requires-Dist: requests
Requires-Dist: pyloggor
